<!-- edited with XMLSpy v2011 (http://www.altova.com) by TeaM DJiNN (TeaM DJiNN) -->
<Protocol>
	<Struct name="MountsContent" relatedclass = "MountModelContent" >
		<Param name="MountsName" index="1" type="int" split2=""/>
		<Param name="MountsLevel" index="3" type="int" split2=""/>
		<Param name="MountsWish" index="4" type="int" split1="" split2=""/>
		<Param name="ClearTime" index="5" type="string" split1="" split2=""/>
		<Param name="MountsItems" index="7" type="intlist" split1="$" split2=""/>
		<Param name="MountsItemsNum" index="8" type="intlist" split1="~" split2=""/>
		<Param name="UpgradeCondition" index="9" type="intlist" split1="~"/>
		<Param name="MountsNextLevelId" index="10" type="int" split1="" split2=""/>
		<Param name="MountsPropertyID" index="11" type="int"/>
		<Param name="ModelLoaderKey" index="12" type="int"/>
		<Param name="MountsStar" index="13" type="int"/>
		<Param name="M_EffectId" index="14" type="stringlist" split1="$"/>
    <Param name="M_AwardIdAndNum" index="15" type="intlist" split1="~"/>
	</Struct>
</Protocol>
